xqfactor/__init__.py
xqfactor/analyzer/__init__.py
xqfactor/analyzer/base.py
xqfactor/analyzer/datafetcher.py
xqfactor/analyzer/ic.py
xqfactor/analyzer/processor.py
xqfactor/analyzer/quantilereturn.py
xqfactor/analyzer/regression.py
xqfactor/config.py
xqfactor/extension.py
xqfactor/factor.py
xqfactor/operators.py
xqfactor-0.1.0.dist-info/WHEEL
xqfactor-0.1.0.dist-info/METADATA
xqfactor-0.1.0.dist-info/RECORD
