Metadata-Version: 2.3
Name: xqfactor
Version: 0.1.0
Summary: Add your description here
Author: xuanqi
Author-email: xuanqi <xuanqiraphael@gmail.com>
Requires-Dist: statsmodels>=0.14.6
Requires-Dist: xqdata[rq]>=0.2.2
Requires-Python: >=3.12
